Workbook

Sheet Assumptions
B2: NTPC LIMITED — Valuation Model | Assumptions & Inputs
A3: # | B3: REGULATORY PARAMETERS (Source: CERC Tariff Regulations 2024-29)
B4: Parameter | C4: Value | D4: Notes / Source
B5: Allowed ROE — Thermal (existing & new) | C5: 0.155 | D5: CERC 2024-29, Regulation 15; unchanged 3 consecutive control periods
B6: Normative Debt Fraction (70:30 rule) | C6: 0.7 | D6: CERC mandates 70% debt, 30% equity in project capital structure
B7: Normative Equity Fraction | C7: =1-C6 -> 0.3 | D7: Formula: 1 − Debt Fraction
B8: Standalone Reg. Equity Dec-2025 (₹ Cr) | C8: 94415 | D8: Source: NTPC Q3 FY26 Earnings Call, 30-Jan-2026, Director Finance
B9: Consolidated Reg. Equity Dec-2025 (₹ Cr) | C9: 118970 | D9: Source: NTPC Q3 FY26 Earnings Call, 30-Jan-2026, Director Finance
B10: CERC Control Period End | C10: Mar-2029 | D10: Current active period; next review expected ~2028-29
A12: # | B12: CAPEX & CAPACITY PLAN FY27–FY31 (Source: Q3 FY26 Earnings Call, NTPC management guidance)
B13: Parameter (₹ Crore unless stated) | C13: FY26A | D13: FY27 | E13: FY28 | F13: FY29 | G13: FY30 | H13: FY31 | I13: FY32 | J13: Assumptions
B14: Gross Group Capex (₹ Cr) | C14: 55920 | D14: 97363 | E14: 112172 | F14: 108636.25 | G14: 108636.25 | H14: 108636.25 | I14: 108636.25 | J14: Guidance of group level capex of 55920 cr in FY26, 97363 in FY27 , 112172 cr in FY28 and to reach 149GW of total capcity by FY32 a cumilative expanditure of 7L cr Is required. Assumed Equal amount of capex from fy29-32
B15: Equity Capex | C15: =C14*$C$7 -> 16776 | D15: =D14*$C$7 -> 29208.9 | E15: =E14*$C$7 -> 33651.6 | F15: =F14*$C$7 -> 32590.875 | G15: =G14*$C$7 -> 32590.875 | H15: =H14*$C$7 -> 32590.875 | I15: =I14*$C$7 -> 32590.875 | J15: 0.3* Gross Capex (CERC Mandate)
B16: Weighted Avg Interest Rate | C16: 0.0605 | D16: 0.0605 | E16: 0.059 | F16: 0.058 | G16: 0.058 | H16: 0.058 | I16: =H16 -> 0.058
B17: Note: Equity Capex = Gross Capex × 30% per CERC 70:30 normative structure. Gross capex annualised from 9M FY26 group capex of ₹33,466 Cr (rate ≈ ₹44,600 Cr/yr). Renewable targets per NGEL management: 5GW FY26, 8GW each FY27 & FY28.

Sheet Historical PnL
B2: NTPC LIMITED — Historical Profit & Loss | INR Crore | FY2016–FY2025
B3: (INR Crore) | C3: FY16 | D3: FY17 | E3: FY18 | F3: FY19 | G3: FY20 | H3: FY21 | I3: FY22 | J3: FY23 | K3: FY24 | L3: FY25
B4: INCOME STATEMENT
B5: Revenue from Operations | C5: 73396 | D5: 82042 | E5: 88083 | F5: 100287 | G5: 109464 | H5: 111531 | I5: 132669 | J5: 176207 | K5: 178525 | L5: 188138
B6: Power & Fuel Cost | C6: 47727 | D6: 52550 | E6: 55691 | F6: 62853 | G6: 65903 | H6: 64821 | I6: 79375 | J6: 111803 | K6: 112041 | L6: 117038
B7: Employee Cost | C7: 4694 | D7: 5243 | E7: 5759 | F7: 5914 | G7: 5897 | H7: 6015 | I7: 7194 | J7: 7459 | K7: 7535 | L7: 7826
B8: Selling & Other Expenses | C8: 1650 | D8: 1632 | E8: 1785 | F8: 2616 | G8: 3319 | H8: 3776 | I8: 4617 | J8: 5937 | K8: 7684 | L8: 9213
B9: Other Expenses / (Income) — net | C9: -1474 | D9: -1544 | E9: -573 | F9: 2723 | G9: -1061 | H9: -1400 | I9: -3535 | J9: -2301 | K9: -6815 | L9: -7746
B10: Operating Profit (EBIT) | C10: =C5-C6-C7-C8-C9 -> 20799 | D10: =D5-D6-D7-D8-D9 -> 24161 | E10: =E5-E6-E7-E8-E9 -> 25421 | F10: =F5-F6-F7-F8-F9 -> 26181 | G10: =G5-G6-G7-G8-G9 -> 35406 | H10: =H5-H6-H7-H8-H9 -> 38319 | I10: =I5-I6-I7-I8-I9 -> 45018 | J10: =J5-J6-J7-J8-J9 -> 53309 | ... L10: =L5-L6-L7-L8-L9 -> 61807
B11: Other Income | C11: 1188 | D11: 1592 | E11: 5576 | F11: 2818 | G11: 8209 | H11: 5021 | I11: 4809 | J11: 2561 | K11: 5146 | L11: 8490
B12: Depreciation | C12: 5771 | D12: 6010 | E12: 7460 | F12: 8669 | G12: 10356 | H12: 12450 | I12: 13788 | J12: 14792 | K12: 16204 | L12: 17401
B13: Finance Costs (Interest) | C13: 3366 | D13: 3753 | E13: 4447 | F13: 5605 | G13: 8189 | H13: 9224 | I13: 9376 | J13: 11447 | K13: 12301 | L13: 13282
B14: Profit Before Tax | C14: 10618 | D14: 13426 | E14: 16154 | F14: 11255 | G14: 21250 | H14: 17390 | I14: 22007 | J14: 23917 | K14: 28142 | L14: 32198
B15: Tax (incl. deferred) | C15: -163 | D15: 2712 | E15: 5653 | F15: -2780 | G15: 9348 | H15: 2421 | I15: 5047 | J15: 6796 | K15: 6809 | L15: 8245
B16: NET PROFIT (PAT) | C16: 10801 | D16: 10720 | E16: 10544 | F16: 13737 | G16: 11600 | H16: 14635 | I16: 16676 | J16: 16913 | K16: 20812 | L16: 23422
B17: Dividend Paid | C17: 2762 | D17: 3941 | E17: 4222 | F17: 6016 | G17: 3117 | H17: 5963 | I17: 6788 | J17: 7030 | K17: 7515 | L17: 8097
B19: RATIOS
B20: Revenue Growth (YoY %) | C20: "-" | D20: =IF(C5>0,D5/C5-1,"-") -> 0.11779934 | E20: =IF(D5>0,E5/D5-1,"-") -> 0.073633017 | F20: =IF(E5>0,F5/E5-1,"-") -> 0.13855114 | G20: =IF(F5>0,G5/F5-1,"-") -> 0.091507374 | H20: =IF(G5>0,H5/G5-1,"-") -> 0.01888292 | I20: =IF(H5>0,I5/H5-1,"-") -> 0.18952578 | J20: =IF(I5>0,J5/I5-1,"-") -> 0.32817011 | K20: =IF(J5>0,K5/J5-1,"-") -> 0.013154982 | L20: =IF(K5>0,L5/K5-1,"-") -> 0.0538468
B21: Operating Margin (%) | C21: =IF(C5>0,C10/C5,"-") -> 0.28338057 | D21: =IF(D5>0,D10/D5,"-") -> 0.2944955 | E21: =IF(E5>0,E10/E5,"-") -> 0.2886028 | F21: =IF(F5>0,F10/F5,"-") -> 0.26106076 | G21: =IF(G5>0,G10/G5,"-") -> 0.32344881 | H21: =IF(H5>0,H10/H5,"-") -> 0.34357264 | I21: =IF(I5>0,I10/I5,"-") -> 0.33932569 | J21: =IF(J5>0,J10/J5,"-") -> 0.30253622 | ... L21: =IF(L5>0,L10/L5,"-") -> 0.32851949
B22: Net Profit Margin (%) | C22: =IF(C5>0,C16/C5,"-") -> 0.14716061 | D22: =IF(D5>0,D16/D5,"-") -> 0.13066478 | E22: =IF(E5>0,E16/E5,"-") -> 0.11970528 | F22: =IF(F5>0,F16/F5,"-") -> 0.13697688 | G22: =IF(G5>0,G16/G5,"-") -> 0.10597091 | H22: =IF(H5>0,H16/H5,"-") -> 0.13121912 | I22: =IF(I5>0,I16/I5,"-") -> 0.12569628 | J22: =IF(J5>0,J16/J5,"-") -> 0.095983701 | ... L22: =IF(L5>0,L16/L5,"-") -> 0.12449372
B23: Return on Equity (%) | C23: =IF('Historical BS'!C7>0,'Historical PnL'!C16/'Historical BS'!C7,"-") -> 0.11794704 | D23: =IF('Historical BS'!D7>0,'Historical PnL'!D16/'Historical BS'!D7,"-") -> 0.10956888 | E23: =IF('Historical BS'!E7>0,'Historical PnL'!E16/'Historical BS'!E7,"-") -> 0.10181242 | F23: =IF('Historical BS'!F7>0,'Historical PnL'!F16/'Historical BS'!F7,"-") -> 0.12336 | G23: =IF('Historical BS'!G7>0,'Historical PnL'!G16/'Historical BS'!G7,"-") -> 0.097610232 | H23: =IF('Historical BS'!H7>0,'Historical PnL'!H16/'Historical BS'!H7,"-") -> 0.11639189 | I23: =IF('Historical BS'!I7>0,'Historical PnL'!I16/'Historical BS'!I7,"-") -> 0.12318466 | J23: =IF('Historical BS'!J7>0,'Historical PnL'!J16/'Historical BS'!J7,"-") -> 0.11503564 | ... L23: =IF('Historical BS'!L7>0,'Historical PnL'!L16/'Historical BS'!L7,"-") -> 0.12724438
B24: Dividend Payout (%) | C24: =IF(C16>0,C17/C16,"-") -> 0.25571706 | D24: =IF(D16>0,D17/D16,"-") -> 0.3676306 | E24: =IF(E16>0,E17/E16,"-") -> 0.4004173 | F24: =IF(F16>0,F17/F16,"-") -> 0.43794133 | G24: =IF(G16>0,G17/G16,"-") -> 0.2687069 | H24: =IF(H16>0,H17/H16,"-") -> 0.4074479 | I24: =IF(I16>0,I17/I16,"-") -> 0.40705205 | J24: =IF(J16>0,J17/J16,"-") -> 0.4156566 | ... L24: =IF(L16>0,L17/L16,"-") -> 0.34570062

Sheet Historical BS
B2: NTPC LIMITED — Balance Sheet & Cash Flow | INR Crore | FY2016–FY2025
B3: (INR Crore) | C3: FY16 | D3: FY17 | E3: FY18 | F3: FY19 | G3: FY20 | H3: FY21 | I3: FY22 | J3: FY23 | K3: FY24 | L3: FY25
B4: EQUITY & LIABILITIES
B5: Share Capital | C5: 8245 | D5: 8245 | E5: 8245 | F5: 9895 | G5: 9895 | H5: 9697 | I5: 9697 | J5: 9697 | K5: 9697 | L5: 9697
B6: Reserves & Surplus | C6: 83330 | D6: 89593 | E6: 95318 | F6: 101462 | G6: 108945 | H6: 116042 | I6: 125677 | J6: 137327 | K6: 151013 | L6: 174374
B7: Total Equity | C7: =C5+C6 -> 91575 | D7: =D5+D6 -> 97838 | E7: =E5+E6 -> 103563 | F7: =F5+F6 -> 111357 | G7: =G5+G6 -> 118840 | H7: =H5+H6 -> 125739 | I7: =I5+I6 -> 135374 | J7: =J5+J6 -> 147024 | ... L7: =L5+L6 -> 184071
B8: Total Borrowings (Debt) | C8: 99424 | D8: 113773 | E8: 130049 | F8: 173058 | G8: 202984 | H8: 210208 | I8: 210707 | J8: 222913 | K8: 237131 | L8: 250096
B9: Debt / Equity (x) | C9: =IF(C7>0,C8/C7,"-") -> 1.0857112 | D9: =IF(D7>0,D8/D7,"-") -> 1.1628713 | E9: =IF(E7>0,E8/E7,"-") -> 1.2557477 | F9: =IF(F7>0,F8/F7,"-") -> 1.5540828 | G9: =IF(G7>0,G8/G7,"-") -> 1.7080444 | H9: =IF(H7>0,H8/H7,"-") -> 1.6717804 | I9: =IF(I7>0,I8/I7,"-") -> 1.5564806 | J9: =IF(J7>0,J8/J7,"-") -> 1.5161674 | ... L9: =IF(L7>0,L8/L7,"-") -> 1.3586931
B10: ASSETS
B11: Net Fixed Assets | C11: 92929 | D11: 104532 | E11: 128245 | F11: 150985 | G11: 187803 | H11: 203245 | I11: 224923 | J11: 240424 | K11: 258934 | L11: 271437
B12: Capital Work-in-Progress | C12: 75046 | D12: 86896 | E12: 83386 | F12: 118397 | G12: 98508 | H12: 97506 | I12: 91126 | J12: 89179 | K12: 87664 | L12: 100859
B13: Trade Receivables (Debtors) | C13: 8289 | D13: 8964 | E13: 8812 | F13: 12364 | G13: 20315 | H13: 28200 | I13: 27971 | J13: 30112 | K13: 33350 | L13: 34720
B14: Cash & Cash Equivalents | C14: 4938 | D14: 3301 | E14: 4388 | F14: 2933 | G14: 3214 | H14: 4388 | I14: 4458 | J14: 4949 | K14: 6847 | L14: 11457
B16: CASH FLOW STATEMENT
B17: Cash from Operations (CFO) | C17: 24125 | D17: 20167 | E17: 19670 | F17: 18686 | G17: 23890 | H17: 32444 | I17: 41788 | J17: 47152 | K17: 40099 | L17: 50436
B18: Cash from Investing (CFI) | C18: -19162 | D18: -24480 | E18: -20678 | F18: -24063 | G18: -29628 | H18: -21034 | I18: -22891 | J18: -26145 | K18: -31456 | L18: -45800
B19: Cash from Financing (CFF) | C19: -3899 | D19: 3138 | E19: 1028 | F19: 4927 | G19: 6004 | H19: -11049 | I19: -19172 | J19: -21217 | K19: -8246 | L19: -4073
B20: Net Change in Cash | C20: =C17+C18+C19 -> 1064 | D20: =D17+D18+D19 -> -1175 | E20: =E17+E18+E19 -> 20 | F20: =F17+F18+F19 -> -450 | G20: =G17+G18+G19 -> 266 | H20: =H17+H18+H19 -> 361 | I20: =I17+I18+I19 -> -275 | J20: =J17+J18+J19 -> -210 | ... L20: =L17+L18+L19 -> 563
B22: DERIVED RATIOS
B23: Debtor Days | C23: =IF('Historical PnL'!C5>0,C13/('Historical PnL'!C5/365),"-") -> 41.221388 | D23: =IF('Historical PnL'!D5>0,D13/('Historical PnL'!D5/365),"-") -> 39.880305 | E23: =IF('Historical PnL'!E5>0,E13/('Historical PnL'!E5/365),"-") -> 36.515332 | F23: =IF('Historical PnL'!F5>0,F13/('Historical PnL'!F5/365),"-") -> 44.999452 | G23: =IF('Historical PnL'!G5>0,G13/('Historical PnL'!G5/365),"-") -> 67.738937 | H23: =IF('Historical PnL'!H5>0,H13/('Historical PnL'!H5/365),"-") -> 92.288243 | I23: =IF('Historical PnL'!I5>0,I13/('Historical PnL'!I5/365),"-") -> 76.954036 | J23: =IF('Historical PnL'!J5>0,J13/('Historical PnL'!J5/365),"-") -> 62.374821 | ... L23: =IF('Historical PnL'!L5>0,L13/('Historical PnL'!L5/365),"-") -> 67.359066
B24: Interest Coverage (x) | C24: =IF('Historical PnL'!C13>0,('Historical PnL'!C14+'Historical PnL'!C13)/'Historical PnL'!C13,"-") -> 4.154486 | D24: =IF('Historical PnL'!D13>0,('Historical PnL'!D14+'Historical PnL'!D13)/'Historical PnL'!D13,"-") -> 4.5774047 | E24: =IF('Historical PnL'!E13>0,('Historical PnL'!E14+'Historical PnL'!E13)/'Historical PnL'!E13,"-") -> 4.6325613 | F24: =IF('Historical PnL'!F13>0,('Historical PnL'!F14+'Historical PnL'!F13)/'Historical PnL'!F13,"-") -> 3.0080285 | G24: =IF('Historical PnL'!G13>0,('Historical PnL'!G14+'Historical PnL'!G13)/'Historical PnL'!G13,"-") -> 3.5949444 | H24: =IF('Historical PnL'!H13>0,('Historical PnL'!H14+'Historical PnL'!H13)/'Historical PnL'!H13,"-") -> 2.8852992 | I24: =IF('Historical PnL'!I13>0,('Historical PnL'!I14+'Historical PnL'!I13)/'Historical PnL'!I13,"-") -> 3.347163 | J24: =IF('Historical PnL'!J13>0,('Historical PnL'!J14+'Historical PnL'!J13)/'Historical PnL'!J13,"-") -> 3.0893684 | ... L24: =IF('Historical PnL'!L13>0,('Historical PnL'!L14+'Historical PnL'!L13)/'Historical PnL'!L13,"-") -> 3.4241831
B25: CFO / PAT (earnings quality) | C25: =IF('Historical PnL'!C16>0,'Historical BS'!C17/'Historical PnL'!C16,"-") -> 2.2335895 | D25: =IF('Historical PnL'!D16>0,'Historical BS'!D17/'Historical PnL'!D16,"-") -> 1.88125 | E25: =IF('Historical PnL'!E16>0,'Historical BS'!E17/'Historical PnL'!E16,"-") -> 1.8655159 | F25: =IF('Historical PnL'!F16>0,'Historical BS'!F17/'Historical PnL'!F16,"-") -> 1.3602679 | G25: =IF('Historical PnL'!G16>0,'Historical BS'!G17/'Historical PnL'!G16,"-") -> 2.0594828 | H25: =IF('Historical PnL'!H16>0,'Historical BS'!H17/'Historical PnL'!H16,"-") -> 2.2168773 | I25: =IF('Historical PnL'!I16>0,'Historical BS'!I17/'Historical PnL'!I16,"-") -> 2.5058767 | J25: =IF('Historical PnL'!J16>0,'Historical BS'!J17/'Historical PnL'!J16,"-") -> 2.7879146 | ... L25: =IF('Historical PnL'!L16>0,'Historical BS'!L17/'Historical PnL'!L16,"-") -> 2.1533601

Sheet Quarterly Data
B1: NTPC LIMITED — Quarterly Performance | INR Crore | Q2 FY24 – Q3 FY26
B2: (INR Crore) | C2: Q2 FY24 | D2: Q3 FY24 | E2: Q4 FY24 | F2: Q1 FY25 | G2: Q2 FY25 | H2: Q3 FY25 | I2: Q4 FY25 | J2: Q1 FY26 | K2: Q2 FY26 | L2: Q3 FY26
B3: QUARTERLY INCOME STATEMENT
B4: Revenue from Operations | C4: 44983 | D4: 42820 | E4: 47628 | F4: 48529 | G4: 44706 | H4: 45069 | I4: 49834 | J4: 47065 | K4: 44786 | L4: 45846
B5: Total Expenses | C5: 32303 | D5: 31458 | E5: 33638 | F5: 35091 | G5: 33041 | H5: 31729 | I5: 35080 | J5: 34485 | K5: 31970 | L5: 31276
B6: Operating Profit (EBIT) | C6: 12680 | D6: 11362 | E6: 13990 | F6: 13438 | G6: 11665 | H6: 13341 | I6: 14754 | J6: 12580 | K6: 12816 | L6: 14570
B7: Operating Margin (%) | C7: =IF(C4>0,C6/C4,"-") -> 0.28188427 | D7: =IF(D4>0,D6/D4,"-") -> 0.2653433 | E7: =IF(E4>0,E6/E4,"-") -> 0.29373478 | F7: =IF(F4>0,F6/F4,"-") -> 0.27690659 | G7: =IF(G4>0,G6/G4,"-") -> 0.26092694 | H7: =IF(H4>0,H6/H4,"-") -> 0.29601278 | I7: =IF(I4>0,I6/I4,"-") -> 0.29606293 | J7: =IF(J4>0,J6/J4,"-") -> 0.26728992 | ... L7: =IF(L4>0,L6/L4,"-") -> 0.31780308
B8: Other Income | C8: 1024 | D8: 2532 | E8: 1400 | F8: 1187 | G8: 3218 | H8: 986 | I8: 4180 | J8: 3240 | K8: 2734 | L8: 1738
B9: Depreciation | C9: 4038 | D9: 4074 | E9: 4271 | F9: 4204 | G9: 4216 | H9: 4318 | I9: 4663 | J9: 4587 | K9: 4816 | L9: 5093
B10: Finance Costs | C10: 2921 | D10: 3250 | E10: 2955 | F10: 3136 | G10: 3621 | H10: 2764 | I10: 3648 | J10: 3468 | K10: 3432 | L10: 3164
B11: Profit Before Tax | C11: 6746 | D11: 6571 | E11: 8164 | F11: 7284 | G11: 7046 | H11: 7245 | I11: 10623 | J11: 7765 | K11: 7301 | L11: 8050
B12: Tax | C12: 2020 | D12: 1362 | E12: 1674 | F12: 1778 | G12: 1666 | H12: 2075 | I12: 2726 | J12: 1657 | K12: 2076 | L12: 2453
B13: NET PROFIT (PAT) | C13: 4615 | D13: 5155 | E13: 6169 | F13: 5474 | G13: 5275 | H13: 5063 | I13: 7611 | J13: 6011 | K13: 5067 | L13: 5489
B14: PAT Margin (%) | C14: =IF(C4>0,C13/C4,"-") -> 0.10259431 | D14: =IF(D4>0,D13/D4,"-") -> 0.12038767 | E14: =IF(E4>0,E13/E4,"-") -> 0.12952465 | F14: =IF(F4>0,F13/F4,"-") -> 0.11279853 | G14: =IF(G4>0,G13/G4,"-") -> 0.11799311 | H14: =IF(H4>0,H13/H4,"-") -> 0.11233886 | I14: =IF(I4>0,I13/I4,"-") -> 0.15272705 | J14: =IF(J4>0,J13/J4,"-") -> 0.12771699 | ... L14: =IF(L4>0,L13/L4,"-") -> 0.11972691

Sheet Comps Beta Table
B2: COMPARABLE COMPANY BETA ANALYSIS — LEVERED / UNLEVERED / RELEVERED
B4: Target Company Assumptions
B5: Target Tax Rate | C5: 0.25 | D5: used for relevering
B6: Target D/E Ratio | C6: =E11 -> 1.27753 | D6: used for relevering
B7: Assume Debt Beta = 0 | C7: =TRUE() -> TRUE | D7: Hamada assumption
B10: Company | C10: Ticker | D10: Levered Beta (Raw) | E10: D/E Ratio (Net) | F10: Tax Rate | G10: Unlevered Beta (Hamada)
B11: NTPC Limited | C11: NTPC.NS | D11: 1.1652792 | E11: 1.27753 | F11: 0.25 | G11: =D11/(1+(1-F11)*E11) -> 0.59509266
B12: NHPC Limited | C12: NHPC.NS | D12: 1.3395075 | E12: 1.0041 | F12: =F11 -> 0.25 | G12: =D12/(1+(1-F12)*E12) -> 0.76409023
B13: SJVN Limited | C13: SJVN.NS | D13: 1.7546184 | E13: 2.02556 | F13: =F12 -> 0.25 | G13: =D13/(1+(1-F13)*E13) -> 0.69650655
B14: Tata Power Company Limited | C14: TATAPOWER.NS | D14: 1.6731934 | E14: 1.5616 | F14: =F13 -> 0.25 | G14: =D14/(1+(1-F14)*E14) -> 0.77063072
B15: Adani Power Limited | C15: ADANIPOWER.NS | D15: 1.1126384 | E15: 0.81251 | F15: =F14 -> 0.25 | G15: =D15/(1+(1-F15)*E15) -> 0.69134493
B17: Mean | D17: =AVERAGE(D11:D15) -> 1.4090474 | E17: =AVERAGE(E11:E15) -> 1.33626 | F17: =AVERAGE(F11:F15) -> 0.25 | G17: =AVERAGE(G11:G15) -> 0.70353302
B18: Median | D18: =MEDIAN(D11:D15) -> 1.3395075 | E18: =MEDIAN(E11:E15) -> 1.27753 | F18: =MEDIAN(F11:F15) -> 0.25 | G18: =MEDIAN(G11:G15) -> 0.69650655
B20: TARGET COMPANY BETA OUTPUT
B21: Selected Unlevered Beta | C21: =G18 -> 0.69650655 | E21: Weighted avg unlevered beta from comps
B22: Target Tax Rate | C22: =$C$5 -> 0.25 | E22: From assumptions
B23: Target D/E Ratio | C23: =$C$6 -> 1.27753 | E23: From assumptions
B24: Relevered Beta (Target) | C24: =C21*(1+(1-$C$22)*$C$23) -> 1.3638626 | E24: Hamada: βL = βU × [1 + (1−t) × D/E]

Sheet WACC 
B1: NTPC LIMITED — WACC MODEL
B2: Blue = input you can change | Black = formula (auto-calculated)
B4: COST OF EQUITY (Ke) | D4: CAPM: Ke = Rf + β × ERP
B5: Risk-Free Rate (Rf) | C5: 0.067 | D5: 10-yr GoI G-Sec yield; RBI Feb 2026
B6: Equity Risk Premium (ERP) | C6: 0.068 | D6: India ERP; Damodaran Jan 2026
B7: Beta (β) | C7: ='Comps Beta Table'!C24 -> 1.3638626 | D7: 5-yr monthly vs Nifty 50; Bloomberg
B8: → Cost of Equity (Ke) | C8: =C5+(C6*C7) -> 0.15974265 | D8: Rf + Beta x ERP
B10: COST OF DEBT (Kd) | D10: After-tax: Kd = Pre-tax Rate × (1 − Tax Rate)
B11: Pre-Tax Interest Rate | C11: 0.0605 | D11: WAIR 6.05% per Q3 FY26 concall
B12: Tax Rate | C12: 0.25 | D12: FY25: Tax / PBT = 25.6%; Screener.in
B13: → After-Tax Cost of Debt (Kd) | C13: =C11*(1-C12) -> 0.045375 | D13: Pre-tax Rate x (1 minus Tax Rate)
B15: CAPITAL STRUCTURE | D15: Market value weights
B16: Market Value of Equity | C16: 370364 | D16: Rs.381.9/share × 969.67 Cr shares; NSE Mar 2026
B17: Market Value of Debt | C17: 250096 | D17: FY25 standalone borrowings (approx. book); Screener.in
B18: Total Capital | C18: =C16+C17 -> 620460 | D18: Equity + Debt
B19: Weight of Equity (We) | C19: =C16/C18 -> 0.59691842 | D19: Equity / Total Capital
B20: Weight of Debt (Wd) | C20: =C17/C18 -> 0.40308158 | D20: Debt / Total Capital
B22: WACC | D22: WACC = We × Ke + Wd × Kd(1−T)
B23: Equity Contribution (We × Ke) | C23: =C19*C8 -> 0.095353332 | D23: Weight of Equity x Ke
B24: Debt Contribution (Wd × Kd) | C24: =C20*C13 -> 0.018289827 | D24: Weight of Debt x After-Tax Kd
B25: ══ WACC | C25: =C23+C24 -> 0.11364316 | D25: We x Ke + Wd x Kd(1-T)
B27: CERC REGULATORY CHECK | D27: How NTPC's allowed return compares to WACC
B28: CERC Allowed ROE | C28: 0.155 | D28: 15.5% on normative equity; CERC 2024-29 tariff order
B29: Standalone Regulated Equity | C29: 94415 | D29: Rs.94,415 Cr as at Dec 31, 2025; Q3 FY26 concall
B30: ROE − WACC Spread | C30: =C28-C25 -> 0.041356841 | D30: Positive = value created above cost of capital
B31: Annual Economic Profit (Rs. Cr) | C31: =C30*C29 -> 3904.7061 | D31: Spread x Regulated Equity (Rs. Cr/year)
B33: NTPC's allowed ROE of 15.5% well exceeds its ~9.7% WACC — every new rupee of regulated equity commissioned creates ~5.8% of incremental value annually.

Sheet DCF Model
B1: REGULATORY EQUITY FCFE MODEL — NTPC CONSOLIDATED | INR Crore
B2: Methodology: FCFE = Net Income − Equity Capex | Net Income = Allowed ROE × Regulatory Equity | Equity Capex = 30% × Gross Capex per CERC 70:30 rule
B3: Parameter (INR Crore unless stated) | C3: 46082 | D3: =C3+365 -> 46447 | E3: =D3+365 -> 46812 | F3: =E3+365 -> 47177 | G3: =F3+365 -> 47542 | H3: =G3+365 -> 47907 | I3: =H3+365 -> 48272
B4: REGULATORY EQUITY BRIDGE
B5: Opening Regulatory Equity Base | C5: 108791 | D5: =C9 -> 125567 | E5: =D9 -> 154775.9 | F5: =E9 -> 188427.5 | G5: =F9 -> 221018.38 | H5: =G9 -> 253609.25 | I5: =H9 -> 286200.12
B6: Net Income (= Allowed ROE × Opening Equity) | C6: =C5*Assumptions!C5 -> 16862.605 | D6: =Assumptions!$C$5*D5 -> 19462.885 | E6: =Assumptions!$C$5*E5 -> 23990.264 | F6: =Assumptions!$C$5*F5 -> 29206.263 | G6: =Assumptions!$C$5*G5 -> 34257.848 | H6: =Assumptions!$C$5*H5 -> 39309.434 | I6: =Assumptions!$C$5*I5 -> 44361.019
B7: Less: Equity Capex (30% × Gross Capex) | C7: =Assumptions!C15 -> 16776 | D7: =Assumptions!D15 -> 29208.9 | E7: =Assumptions!E15 -> 33651.6 | F7: =Assumptions!F15 -> 32590.875 | G7: =Assumptions!G15 -> 32590.875 | H7: =Assumptions!H15 -> 32590.875 | I7: =Assumptions!I15 -> 32590.875
B8: FCFE (= Net Income − Equity Capex) | C8: =C6-C7 -> 86.605 | D8: =D6-D7 -> -9746.015 | E8: =E6-E7 -> -9661.3355 | F8: =F6-F7 -> -3384.6125 | G8: =G6-G7 -> 1666.9731 | H8: =H6-H7 -> 6718.5587 | I8: =I6-I7 -> 11770.144
B9: Closing Regulatory Equity Base | C9: =C5+C7 -> 125567 | D9: =D5+D7 -> 154775.9 | E9: =E5+E7 -> 188427.5 | F9: =F5+F7 -> 221018.38 | G9: =G5+G7 -> 253609.25 | H9: =H5+H7 -> 286200.12 | I9: =I5+I7 -> 318791
B11: DISCOUNTING @ Cost of Equity
B12: Year Number | C12: 1 | D12: 2 | E12: 3 | F12: 4 | G12: 5 | H12: 6 | I12: 7
B13: Discount Factor 1/(1+CoE)^n | C13: =1/(1+'WACC '!$C$8)^C12 -> 0.86226026 | D13: =1/(1+'WACC '!$C$8)^D12 -> 0.74349275 | E13: =1/(1+'WACC '!$C$8)^E12 -> 0.64108425 | F13: =1/(1+'WACC '!$C$8)^F12 -> 0.55278147 | G13: =1/(1+'WACC '!$C$8)^G12 -> 0.47664149 | H13: =1/(1+'WACC '!$C$8)^H12 -> 0.41098902 | I13: =1/(1+'WACC '!$C$8)^I12 -> 0.3543795
B14: PV of FCFE | C14: =C9*C13 -> 108271.43 | D14: =D9*D13 -> 115074.76 | E14: =E9*E13 -> 120797.9 | F14: =F9*F13 -> 122174.86 | G14: =G9*G13 -> 120880.69 | H14: =H9*H13 -> 117625.11 | I14: =I9*I13 -> 112972.99
B16: TERMINAL VALUE (Gordon Growth Model)
B17: Cost of Equity | C17: ='WACC '!C8 -> 0.15974265
B18: Terminal Growth Rate (g) | C18: 0.05
B19: FCFE in Year 8 (= FCFE_Y5 × (1+g)) | C19: =I14*(1+C18) -> 118621.64
B20: Terminal Value (= FCFE_Y6 / (CoE − g)) | C20: =C19/(C17-C18) -> 1080907.4
B21: PV of Terminal Value (discounted back 5 yrs) | C21: =C20/(1+C17)^I12 -> 383051.41
B23: EQUITY VALUATION SUMMARY
B24: Sum of PV of Explicit Period FCFE (FY27–FY31) | C24: =SUM(C14:I14) -> 817797.75
B25: PV of Terminal Value | C25: =C21 -> 383051.41
B26: TOTAL EQUITY VALUE (INR Crore) | C26: =C24+C25 -> 1200849.2
B27: Shares Outstanding (Crore) | C27: 970
B28: INTRINSIC VALUE PER SHARE (INR) | C28: =C26/C27 -> 1237.9888
B29: Current Market Price (INR) | C29: 382
B30: Margin of Safety / (Premium to Market) | C30: =(C28/C29)-1 -> 2.2408084
